.DS_Store
bsed/__init__.py
bsed/configuration.py
bsed/definitions.py
bsed/interpreter.py
bsed/parser.py
bsed/special_chars.py
bsed/token_tree.py
bsed/translator.py
bsed/config/CONFIG_README.md
bsed/config/command_translations.json
bsed/config/line_condition_translations.json
bsed/config/token_tree.json
tests/__init__.py
tests/context.py
tests/test_append.py
tests/test_clear.py
tests/test_delete.py
tests/test_escaped_symbols.py
tests/test_in_place_flag.py
tests/test_nonescaped_symbols.py
tests/test_on_lines_containing.py
tests/test_on_lines_ending_with.py
tests/test_on_lines_m_to_n.py
tests/test_on_lines_starting_with.py
tests/test_prepend.py
tests/test_replace.py
tests/test_select.py
tests/test_wrap.py
bsed-0.2.5.dist-info/LICENSE
bsed-0.2.5.dist-info/METADATA
bsed-0.2.5.dist-info/WHEEL
bsed-0.2.5.dist-info/entry_points.txt
bsed-0.2.5.dist-info/top_level.txt
bsed-0.2.5.dist-info/RECORD
